Metadata-Version: 2.1
Name: mNSF
Version: 0.1.5
Summary: multi-sample non-negative spatial factorization
Home-page: https://github.com/hansenlab/mNSF/
Download-URL: https://github.com/user/reponame/archive/v_01.tar.gz
Author: Yi Wang, Kyla Woyshner, Chaichontat Sriworarat, Loyal Goff, Genevieve Stein-O'Brien, Kasper D. Hansen
Author-email: yiwangthu4@gmail.com
License: MIT
Keywords: spatial,factorization,multi-sample
Classifier: Development Status :: 3 - Alpha
Classifier: Intended Audience :: Developers
Classifier: Topic :: Software Development :: Build Tools
Classifier: License :: OSI Approved :: MIT License
Classifier: Programming Language :: Python :: 3.10
Requires-Dist: anndata
Requires-Dist: click
Requires-Dist: dill
Requires-Dist: matplotlib
Requires-Dist: numpy
Requires-Dist: pandas
Requires-Dist: pip
Requires-Dist: scanpy
Requires-Dist: squidpy
Requires-Dist: tensorflow==2.13.*
Requires-Dist: tensorflow-probability==0.21.*
